AUTHORS
COPYING
COPYING.LESSER
LICENSE
MANIFEST.in
README.rst
TODO
setup.py
doc/man/man1/instant-clean.1.gz
doc/man/man1/instant-showcache.1.gz
doc/sphinx/Makefile
doc/sphinx/README
doc/sphinx/source/conf.py
doc/sphinx/source/index.rst
doc/sphinx/source/installation.rst
doc/sphinx/source/manual.rst
doc/sphinx/source/releases.rst
doc/sphinx/source/releases/next.rst
doc/sphinx/source/releases/v1.6.0.rst
doc/sphinx/source/releases/v2016.1.0.rst
doc/sphinx/source/releases/v2016.2.0.rst
doc/sphinx/source/releases/v2017.1.0.post1.rst
doc/sphinx/source/releases/v2017.1.0.rst
doc/sphinx/source/releases/v2017.2.0.rst
fenics_instant.egg-info/PKG-INFO
fenics_instant.egg-info/SOURCES.txt
fenics_instant.egg-info/dependency_links.txt
fenics_instant.egg-info/requires.txt
fenics_instant.egg-info/top_level.txt
instant/__init__.py
instant/build.py
instant/cache.py
instant/codegeneration.py
instant/config.py
instant/inlining.py
instant/locking.py
instant/output.py
instant/paths.py
instant/signatures.py
instant/swig/numpy.i
scripts/instant-clean
scripts/instant-showcache
test/_test_ode_omp.py
test/_test_omp.py
test/_test_vmtk.py
test/_test_vtk.py
test/clean.py
test/pytest.ini
test/rerun_tests.py
test/run_omp_test.sh
test/run_pychecker.py
test/run_tests.py
test/some_func.h
test/test01.py
test/test02.py
test/test03.py
test/test04.py
test/test05.py
test/test06.py
test/test07.py
test/test08.py
test/test10.py
test/test11.py
test/test12.py
test/test15.py
test/test16.py
test/test17.py
test/test18.py
test/test19.py
test/test20.py
test/test21.py
test/test_instant_system_calls.py
test/test_ode.py
test/u000000.vtu
test/zombie_model.py