Metadata-Version: 1.1
Name: fenics-instant
Version: 2017.2.0
Summary: Instant Inlining of C/C++ in Python
Home-page: https://bitbucket.org/fenics-project/instant/
Author: Magne Westlie, Kent-Andre Mardal, Martin Sandve Alnes and Ilmar M. Wilbers
Author-email: fenics-dev@googlegroups.com
License: UNKNOWN
Download-URL: https://bitbucket.org/fenics-project/instant/downloads/fenics-instant-2017.2.0.tar.gz
Platform: UNKNOWN
Classifier: Development Status :: 5 - Production/Stable
Classifier: Intended Audience :: Developers
Classifier: Intended Audience :: Science/Research
Classifier: License :: OSI Approved :: GNU Lesser General Public License v3 or later (LGPLv3+)
Classifier: Operating System :: POSIX
Classifier: Operating System :: POSIX :: Linux
Classifier: Operating System :: MacOS :: MacOS X
Classifier: Operating System :: Microsoft :: Windows
Classifier: Programming Language :: Python
Classifier: Programming Language :: Python :: 2
Classifier: Programming Language :: Python :: 2.7
Classifier: Programming Language :: Python :: 3
Classifier: Programming Language :: Python :: 3.4
Classifier: Programming Language :: Python :: 3.5
Classifier: Programming Language :: Python :: 3.6
Classifier: Topic :: Scientific/Engineering :: Mathematics
Classifier: Topic :: Software Development :: Libraries :: Python Modules
